{
    "id": 126990321,
    "name": "Ship Major",
    "author": "Kawby",
    "creators": ["Kawby"],
    "verifier": "Kawby",
    "verification": "https://youtu.be/HMUsrBIhgGw",
    "percentToQualify": "100",
    "password": "Free Copy",
    "records": [
        {
            "user": "Fireball157",
            "link": "https://www.youtube.com/watch?v=QZYQ4ZPyv1k",
            "percent": 100,
            "hz": 240
        },
      {
            "user": "secretagentm7",
            "link": "https://medal.tv/games/geometry-dash/clips/mnzHcP4a8pr3G-aCB",
            "percent": 100,
            "hz": 240
      }
    ]
}
