{
    "id": 135150161,
    "name": "UpsideDown Airplane",
    "author": "secretagentm7",
    "creators": ["secretagentm7"],
    "verifier": "secretagentm7",
    "verification": "https://medal.tv/games/geometry-dash/clips/kbkn0N2nacEqbD1ZD",
    "percentToQualify": "100",
    "password": "Free Copy",
    "records": [
        {
          "user": "Fireball157",
          "link": "https://outplayed.tv/geometry-dash/D8J1R1",
          "percent": 100,
          "hz": 240
       },
        {
          "user": "Kawby",
          "link": "",
          "percent": 100,
          "hz": 240
       },
        {
          "user": "SuperSeal22",
          "link": "",
          "percent": 100,
          "hz": 240
       },
        {
          "user": "Talkative_Toad",
          "link": "",
          "percent": 100,
          "hz": 240
       },
        {
          "user": "GDtheChroma",
          "link": "",
          "percent": 100,
          "hz": 240
       }
    ]
}
